[{"id":1,"nombre":"Esteban","apellido":"Zuniga","correo":"eban316@gmail.com","password":"12345"},{"id":2,"nombre":"Carlos","apellido":"Maldonado","correo":"cfmz@gmail.com","password":"1234"},{"id":3,"nombre":"Felipe","apellido":"Perez de Arce","correo":"fperezdearcer@gmail.com","password":"12345"},{"id":4,"correo":"raul123@gmail.com","nombre":"Raul","apellido":"Zuniga","password":"12345"},{"id":5,"correo":"raul123@gmail.com","nombre":"Raul","apellido":"Zuniga","password":"12345"},{"id":6,"correo":"gabrielapizarroc@gmail.com","nombre":"Gabriela","apellido":"Pizarro","password":"123456789"}]